setup.cfg
setup.py
hmc/__init__.py
hmc/datasets.py
hmc/exceptions.py
hmc/hmc.py
hmc/metrics.py
hmc.egg-info/PKG-INFO
hmc.egg-info/SOURCES.txt
hmc.egg-info/dependency_links.txt
hmc.egg-info/top_level.txt