Metadata-Version: 1.1
Name: hmc
Version: 0.3
Summary: Decision tree based hierachical multi-classifier
Home-page: https://github.com/davidwarshaw/hmc
Author: David Warshaw
Author-email: david.warshaw@gmail.com
License: UNKNOWN
Platform: UNKNOWN
Requires: sklearn
Requires: numpy
Requires: pandas
